{"onlineId": "236QD5H", "globalObjectKey": "ecd151bd-224b-4f37-a471-9fa68e4dee22", "areas": {"landArea": {"unit": "squaremeter"}, "livingArea": {"unit": "squaremeter"}}, "address": {"isPublic": true, "longitude": 9.3722, "latitude": 47.4241, "street": "Hint. Sch\u00fctzengasse/Brunnegg", "city": "St. Gallen", "zip": "9000", "district": "Innenstadt", "locationId": [516424, 517048, 517049, 517052, 519000]}, "name": "Einstellplatz im Zentrum von St. Gallen", "creationDate": "2021-11-09", "broker": {"type": "commercial", "logo": {"small": {"uri": "https://filestore.immowelt.de/logo/left_44613a8281364159b6b2807660fd9e0c.jpg"}, "large": {"uri": "https://filestore.immowelt.de/logo/44613a8281364159b6b2807660fd9e0c.jpg"}}, "companyName": "Apleona GVA AG", "globalUserId": 1374391, "brokerContact": {"name": "Villabruna Angela"}}, "rooms": 0.0, "price": {"currency": "CHF", "value": 350.0, "type": "rent-warm", "attribute": "INKL_NEBENKOSTEN"}, "estateType": "GARAGE_STELLPLATZ", "distributionType": "ZUR_MIETE", "images": [{"thumbnail": {"size": 100, "uri": "https://media-thumbs1.immowelt.org/7/0/c/0/100_3ece1e7a46d34b48b0531cf27a580c07.jpg"}, "small": {"size": 300, "uri": "https://media-thumbs1.immowelt.org/7/0/c/0/300_3ece1e7a46d34b48b0531cf27a580c07.jpg"}, "medium": {"size": 400, "uri": "https://media-pics1.immowelt.org/7/0/c/0/3ece1e7a46d34b48b0531cf27a580c07.jpg"}, "large": {"size": 600, "uri": "https://media-pics1.immowelt.org/7/0/c/0/600_3ece1e7a46d34b48b0531cf27a580c07.jpg"}}], "equipment": [{"type": "Equipment", "value": "PERSONENAUFZUG"}]}