{"onlineId": "232UD5H", "globalObjectKey": "bc357270-fb04-4715-bb0a-eb7754e022f7", "areas": {"landArea": {"unit": "squaremeter"}, "livingArea": {"unit": "squaremeter"}}, "address": {"isPublic": true, "longitude": 6.5771, "latitude": 46.5267, "street": "Rue de la Mouline 2/8", "city": "Chavannes-Renens", "zip": "1022", "locationId": [516424, 518086, 518392, 518397]}, "name": "Place de moto \u00e0 louer dans parking int\u00e9rieur proche EPFL", "creationDate": "2021-11-23", "broker": {"type": "commercial", "logo": {"small": {"uri": "https://filestore.immowelt.de/logo/left_44613a8281364159b6b2807660fd9e0c.jpg"}, "large": {"uri": "https://filestore.immowelt.de/logo/44613a8281364159b6b2807660fd9e0c.jpg"}}, "companyName": "Apleona GVA AG", "globalUserId": 1374391, "brokerContact": {"name": "Strahm Mathias"}}, "rooms": 0.0, "price": {"currency": "CHF", "value": 20.0, "type": "rent-warm", "attribute": "INKL_NEBENKOSTEN"}, "estateType": "GARAGE_STELLPLATZ", "distributionType": "ZUR_MIETE", "images": [{"thumbnail": {"size": 100, "uri": "https://media-thumbs1.immowelt.org/7/9/0/4/100_456378d0a8f04f599ad5a6b7be624097.jpg"}, "small": {"size": 300, "uri": "https://media-thumbs1.immowelt.org/7/9/0/4/300_456378d0a8f04f599ad5a6b7be624097.jpg"}, "medium": {"size": 400, "uri": "https://media-pics1.immowelt.org/7/9/0/4/456378d0a8f04f599ad5a6b7be624097.jpg"}, "large": {"size": 600, "uri": "https://media-pics1.immowelt.org/7/9/0/4/600_456378d0a8f04f599ad5a6b7be624097.jpg"}}]}