{"onlineId": "253WM55", "globalObjectKey": "3aa7e252-76d2-4936-b37d-73764cd2ea84", "areas": {"landArea": {"unit": "squaremeter"}, "livingArea": {"value": 160.0, "unit": "squaremeter"}}, "address": {"isPublic": false, "city": "Le Grand-Saconnex", "zip": "1218", "locationId": [516424, 518613, 518636]}, "name": "Agence de Relocation. Appartement 5 pi\u00e8ces, Route de Colovrex. Proche des commerces et des commodit\u00e9s.", "creationDate": "2022-04-18", "broker": {"type": "commercial", "companyName": "Just Immo S\u00e0rl", "globalUserId": 1651884, "brokerContact": {"name": "Ichem Cherchari"}}, "rooms": 5.0, "price": {"currency": "CHF", "value": 3569.0, "type": "rent-cold"}, "estateType": "WOHNUNG", "distributionType": "ZUR_MIETE", "images": [{"thumbnail": {"size": 100, "uri": "https://media-thumbs2.immowelt.org/f/1/6/9/100_82ca026eed1f49cbb9ce5f09d04f961f.jpg"}, "small": {"size": 300, "uri": "https://media-thumbs2.immowelt.org/f/1/6/9/300_82ca026eed1f49cbb9ce5f09d04f961f.jpg"}, "medium": {"size": 400, "uri": "https://media-pics2.immowelt.org/f/1/6/9/82ca026eed1f49cbb9ce5f09d04f961f.jpg"}, "large": {"size": 600, "uri": "https://media-pics2.immowelt.org/f/1/6/9/600_82ca026eed1f49cbb9ce5f09d04f961f.jpg"}}, {"thumbnail": {"size": 100, "uri": "https://media-thumbs2.immowelt.org/d/9/9/8/100_a5dd0b7b3f254ab7ac290da62fef899d.jpg"}, "small": {"size": 300, "uri": "https://media-thumbs2.immowelt.org/d/9/9/8/300_a5dd0b7b3f254ab7ac290da62fef899d.jpg"}, "medium": {"size": 400, "uri": "https://media-pics2.immowelt.org/d/9/9/8/a5dd0b7b3f254ab7ac290da62fef899d.jpg"}, "large": {"size": 600, "uri": "https://media-pics2.immowelt.org/d/9/9/8/600_a5dd0b7b3f254ab7ac290da62fef899d.jpg"}}, {"thumbnail": {"size": 100, "uri": "https://media-thumbs2.immowelt.org/8/5/f/9/100_a1616e155560488ea1edee2bdd249f58.jpg"}, "small": {"size": 300, "uri": "https://media-thumbs2.immowelt.org/8/5/f/9/300_a1616e155560488ea1edee2bdd249f58.jpg"}, "medium": {"size": 400, "uri": "https://media-pics2.immowelt.org/8/5/f/9/a1616e155560488ea1edee2bdd249f58.jpg"}, "large": {"size": 600, "uri": "https://media-pics2.immowelt.org/8/5/f/9/600_a1616e155560488ea1edee2bdd249f58.jpg"}}, {"thumbnail": {"size": 100, "uri": "https://media-thumbs2.immowelt.org/8/9/7/f/100_0c07e6f3772347179eb15eb0cfc0f798.jpg"}, "small": {"size": 300, "uri": "https://media-thumbs2.immowelt.org/8/9/7/f/300_0c07e6f3772347179eb15eb0cfc0f798.jpg"}, "medium": {"size": 400, "uri": "https://media-pics2.immowelt.org/8/9/7/f/0c07e6f3772347179eb15eb0cfc0f798.jpg"}, "large": {"size": 600, "uri": "https://media-pics2.immowelt.org/8/9/7/f/600_0c07e6f3772347179eb15eb0cfc0f798.jpg"}}], "equipment": [{"type": "Equipment", "value": "FERNBLICK"}]}