{"onlineId": "24DB35U", "globalObjectKey": "781333ba-733d-4c39-803b-b09e98baba48", "areas": {"landArea": {"unit": "squaremeter"}, "livingArea": {"unit": "squaremeter"}}, "address": {"isPublic": true, "longitude": 8.9269, "latitude": 47.2408, "street": "EH M\u00fchlestr. 3 EP Nr. 38-57", "city": "Eschenbach SG", "zip": "8733", "locationId": [516424, 517048, 517099, 517109]}, "name": "Motorradpl\u00e4tze zu vermieten", "creationDate": "2022-03-23", "broker": {"type": "commercial", "logo": {"small": {"uri": "https://filestore.immowelt.de/logo/left_44613a8281364159b6b2807660fd9e0c.jpg"}, "large": {"uri": "https://filestore.immowelt.de/logo/44613a8281364159b6b2807660fd9e0c.jpg"}}, "companyName": "Apleona GVA AG", "globalUserId": 1374391, "brokerContact": {"name": "Wyss Rebecca"}}, "rooms": 0.0, "price": {"currency": "CHF", "value": 30.0, "type": "rent-warm", "attribute": "INKL_NEBENKOSTEN"}, "estateType": "GARAGE_STELLPLATZ", "distributionType": "ZUR_MIETE", "images": [{"thumbnail": {"size": 100, "uri": "https://media-thumbs1.immowelt.org/3/f/5/e/100_0d6b105e23724923986eb969a2abe5f3.jpg"}, "small": {"size": 300, "uri": "https://media-thumbs1.immowelt.org/3/f/5/e/300_0d6b105e23724923986eb969a2abe5f3.jpg"}, "medium": {"size": 400, "uri": "https://media-pics1.immowelt.org/3/f/5/e/0d6b105e23724923986eb969a2abe5f3.jpg"}, "large": {"size": 600, "uri": "https://media-pics1.immowelt.org/3/f/5/e/600_0d6b105e23724923986eb969a2abe5f3.jpg"}}]}