{"onlineId": "235CC52", "globalObjectKey": "04f33fb0-300d-4ca8-8892-27a3372db5ce", "areas": {"landArea": {"unit": "squaremeter"}, "livingArea": {"value": 12.0, "unit": "squaremeter"}}, "address": {"isPublic": true, "longitude": 7.2748, "latitude": 47.1422, "street": "S\u00fcdstrasse", "city": "Biel/Bienne", "zip": "2504", "district": "Mett/M\u00e2che", "locationId": [516424, 517486, 517528, 517529, 519216]}, "name": "Freie Parkpl\u00e4tze finden Sie hier!", "creationDate": "2021-10-11", "broker": {"type": "commercial", "companyName": "Helvetia Versicherungen ", "globalUserId": 2639504, "brokerContact": {"name": "Schaub Anna"}}, "rooms": 0.0, "price": {"currency": "CHF", "value": 117.0, "type": "rent-warm", "attribute": "INKL_NEBENKOSTEN"}, "estateType": "GARAGE_STELLPLATZ", "distributionType": "ZUR_MIETE", "equipment": [{"type": "Equipment", "value": "GARAGE"}]}