{"onlineId": "2W68N4J", "globalObjectKey": "9eb9b3b5-d2b0-43e7-bc4d-b35512f0e414", "areas": {"landArea": {"unit": "squaremeter"}, "livingArea": {"unit": "squaremeter"}}, "address": {"isPublic": true, "longitude": 7.5124, "latitude": 47.2084, "street": "Buchenstrasse 1-11/ Fichtenweg", "city": "Solothurn", "zip": "4500", "locationId": [516424, 516768, 516873, 516874]}, "name": "Motorradabstellpl\u00e4tze", "creationDate": "2020-09-03", "broker": {"type": "commercial", "logo": {"small": {"uri": "https://filestore.immowelt.de/logo/left_44613a8281364159b6b2807660fd9e0c.jpg"}, "large": {"uri": "https://filestore.immowelt.de/logo/44613a8281364159b6b2807660fd9e0c.jpg"}}, "companyName": "Apleona GVA AG", "globalUserId": 1374391, "brokerContact": {"name": "Gallaz Mich\u00e8le"}}, "rooms": 0.0, "price": {"currency": "CHF", "value": 30.0, "type": "rent-warm", "attribute": "INKL_NEBENKOSTEN"}, "estateType": "GARAGE_STELLPLATZ", "distributionType": "ZUR_MIETE", "images": [{"thumbnail": {"size": 100, "uri": "https://media-thumbs1.immowelt.org/7/1/f/5/100_1e5dcaf05f184f3384eef05edce65f17.jpg"}, "small": {"size": 300, "uri": "https://media-thumbs1.immowelt.org/7/1/f/5/300_1e5dcaf05f184f3384eef05edce65f17.jpg"}, "medium": {"size": 400, "uri": "https://media-pics1.immowelt.org/7/1/f/5/1e5dcaf05f184f3384eef05edce65f17.jpg"}, "large": {"size": 600, "uri": "https://media-pics1.immowelt.org/7/1/f/5/600_1e5dcaf05f184f3384eef05edce65f17.jpg"}}]}