{"onlineId": "24AAH5N", "globalObjectKey": "4a048b1a-4439-4f35-b345-28c4041d4097", "areas": {"landArea": {"unit": "squaremeter"}, "livingArea": {"value": 18.5, "unit": "squaremeter"}}, "address": {"isPublic": true, "longitude": 8.9137, "latitude": 47.2783, "street": "T\u00f6sstalstrasse 45 - 51", "city": "Wald ZH", "zip": "8636", "locationId": [516424, 516426, 516513, 516523]}, "name": "zentral gelegene 1.5-Zimmerwohnung", "creationDate": "2022-03-08", "broker": {"type": "commercial", "logo": {"small": {"uri": "https://filestore.immowelt.de/logo/left_44613a8281364159b6b2807660fd9e0c.jpg"}, "large": {"uri": "https://filestore.immowelt.de/logo/44613a8281364159b6b2807660fd9e0c.jpg"}}, "companyName": "Apleona GVA AG", "globalUserId": 1374391, "brokerContact": {"name": "Frick Ramona"}}, "rooms": 1.5, "price": {"currency": "CHF", "value": 780.0, "type": "rent-warm", "attribute": "INKL_NEBENKOSTEN"}, "estateType": "WOHNUNG", "distributionType": "ZUR_MIETE", "images": [{"thumbnail": {"size": 100, "uri": "https://media-thumbs2.immowelt.org/8/8/d/b/100_53abd410a85844268d855e6039f3bd88.jpg"}, "small": {"size": 300, "uri": "https://media-thumbs2.immowelt.org/8/8/d/b/300_53abd410a85844268d855e6039f3bd88.jpg"}, "medium": {"size": 400, "uri": "https://media-pics2.immowelt.org/8/8/d/b/53abd410a85844268d855e6039f3bd88.jpg"}, "large": {"size": 600, "uri": "https://media-pics2.immowelt.org/8/8/d/b/600_53abd410a85844268d855e6039f3bd88.jpg"}}, {"thumbnail": {"size": 100, "uri": "https://media-thumbs1.immowelt.org/3/1/f/0/100_e54ba3f85d3249a8913b2e72ec380f13.jpg"}, "small": {"size": 300, "uri": "https://media-thumbs1.immowelt.org/3/1/f/0/300_e54ba3f85d3249a8913b2e72ec380f13.jpg"}, "medium": {"size": 400, "uri": "https://media-pics1.immowelt.org/3/1/f/0/e54ba3f85d3249a8913b2e72ec380f13.jpg"}, "large": {"size": 600, "uri": "https://media-pics1.immowelt.org/3/1/f/0/600_e54ba3f85d3249a8913b2e72ec380f13.jpg"}}, {"thumbnail": {"size": 100, "uri": "https://media-thumbs2.immowelt.org/a/0/5/b/100_2980e3626a6841d4870ffbc08a9eb50a.jpg"}, "small": {"size": 300, "uri": "https://media-thumbs2.immowelt.org/a/0/5/b/300_2980e3626a6841d4870ffbc08a9eb50a.jpg"}, "medium": {"size": 400, "uri": "https://media-pics2.immowelt.org/a/0/5/b/2980e3626a6841d4870ffbc08a9eb50a.jpg"}, "large": {"size": 600, "uri": "https://media-pics2.immowelt.org/a/0/5/b/600_2980e3626a6841d4870ffbc08a9eb50a.jpg"}}, {"thumbnail": {"size": 100, "uri": "https://media-thumbs1.immowelt.org/1/b/5/9/100_91a8f6efc650403b8210b678ef8f95b1.jpg"}, "small": {"size": 300, "uri": "https://media-thumbs1.immowelt.org/1/b/5/9/300_91a8f6efc650403b8210b678ef8f95b1.jpg"}, "medium": {"size": 400, "uri": "https://media-pics1.immowelt.org/1/b/5/9/91a8f6efc650403b8210b678ef8f95b1.jpg"}, "large": {"size": 600, "uri": "https://media-pics1.immowelt.org/1/b/5/9/600_91a8f6efc650403b8210b678ef8f95b1.jpg"}}], "equipment": [{"type": "Equipment", "value": "KABELANSCHLUSS"}, {"type": "Equipment", "value": "HAUSTIERE_ERLAUBT"}]}