{"onlineId": "22D4758", "globalObjectKey": "1b6717e4-0383-421c-84a3-40737c4ddada", "areas": {"landArea": {"unit": "squaremeter"}, "livingArea": {"unit": "squaremeter"}}, "address": {"isPublic": true, "longitude": 7.5459, "latitude": 47.4985, "street": "Im Hofacker 2 - 16, AEH", "city": "Therwil", "zip": "4106", "locationId": [516424, 516892, 516893, 516908]}, "name": "Haben Sie genug von der Parkplatzsuche? Wir haben die L\u00f6sung!", "creationDate": "2021-07-27", "broker": {"type": "commercial", "companyName": "Helvetia Versicherungen ", "globalUserId": 2639504, "brokerContact": {"name": "Gygax Evelyn"}}, "rooms": 0.0, "price": {"currency": "CHF", "value": 150.0, "type": "rent-warm", "attribute": "INKL_NEBENKOSTEN"}, "estateType": "GARAGE_STELLPLATZ", "distributionType": "ZUR_MIETE"}