{"onlineId": "2ZUF44X", "globalObjectKey": "52755e40-681b-4b92-b995-1c6dfbd3c8ca", "areas": {"landArea": {"unit": "squaremeter"}, "livingArea": {"value": 106.1, "unit": "squaremeter"}}, "address": {"isPublic": true, "longitude": 7.5368, "latitude": 47.2087, "street": "Barf\u00fcssergasse 13", "city": "Solothurn", "zip": "4500", "locationId": [516424, 516768, 516873, 516874]}, "name": "Mitten in der Altstadt, originell und modern Wohnen!", "creationDate": "2021-07-01", "broker": {"type": "commercial", "companyName": "Helvetia Versicherungen ", "globalUserId": 2639504, "brokerContact": {"name": "K\u00f6hli Franziska"}}, "rooms": 3.5, "price": {"currency": "CHF", "value": 2050.0, "type": "rent-warm", "attribute": "INKL_NEBENKOSTEN"}, "estateType": "WOHNUNG", "distributionType": "ZUR_MIETE", "equipment": [{"type": "Equipment", "value": "PERSONENAUFZUG"}, {"type": "Equipment", "value": "KABELANSCHLUSS"}, {"type": "Equipment", "value": "ISDN"}, {"type": "Equipment", "value": "HAUSTIERE_ERLAUBT"}]}