{"onlineId": "2WYQV46", "globalObjectKey": "efb246e1-b83d-4044-a458-94538bbf8cff", "address": {"isPublic": true, "longitude": 7.3962, "latitude": 46.9357, "street": "Weidmattweg 24 ", "city": "Bern", "zip": "3018", "district": "B\u00fcmpliz", "locationId": [516424, 517486, 517679, 517681, 518969]}, "name": "Lager / Schopf ", "creationDate": "2020-08-05", "broker": {"type": "commercial", "logo": {"small": {"uri": "https://filestore.immowelt.de/logo/left_fc130bd2488f4ef39e43e4b8ebe5ca75.jpg"}, "large": {"uri": "https://filestore.immowelt.de/logo/fc130bd2488f4ef39e43e4b8ebe5ca75.jpg"}}, "companyName": "IMMOBILIARIX", "globalUserId": 5712449, "brokerContact": {"name": "Herr Danilo Francone", "image": {"small": {"uri": "https://filestore.immowelt.de/profilbilder/150_e321ae89435a4198b22d7ab95be0fdc3.jpg"}, "large": {"uri": "https://filestore.immowelt.de/profilbilder/e321ae89435a4198b22d7ab95be0fdc3.jpg"}}}, "visiting": ["ONLINE", "SINGLE"]}, "price": {"currency": "CHF", "value": 75.0, "type": "rent-cold"}, "estateType": "GARAGE_STELLPLATZ", "distributionType": "ZUR_MIETE", "images": [{"thumbnail": {"size": 100, "uri": "https://media-thumbs2.immowelt.org/e/0/e/5/100_f241a111ced042429f4abf47e64c5e0e.jpg"}, "small": {"size": 300, "uri": "https://media-thumbs2.immowelt.org/e/0/e/5/300_f241a111ced042429f4abf47e64c5e0e.jpg"}, "medium": {"size": 400, "uri": "https://media-pics2.immowelt.org/e/0/e/5/f241a111ced042429f4abf47e64c5e0e.jpg"}, "large": {"size": 600, "uri": "https://media-pics2.immowelt.org/e/0/e/5/600_f241a111ced042429f4abf47e64c5e0e.jpg"}}, {"thumbnail": {"size": 100, "uri": "https://media-thumbs2.immowelt.org/f/c/8/6/100_58952f311c1b4c44854dd38f48bd68cf.jpg"}, "small": {"size": 300, "uri": "https://media-thumbs2.immowelt.org/f/c/8/6/300_58952f311c1b4c44854dd38f48bd68cf.jpg"}, "medium": {"size": 400, "uri": "https://media-pics2.immowelt.org/f/c/8/6/58952f311c1b4c44854dd38f48bd68cf.jpg"}, "large": {"size": 600, "uri": "https://media-pics2.immowelt.org/f/c/8/6/600_58952f311c1b4c44854dd38f48bd68cf.jpg"}}]}